LICENCE.txt
MANIFEST.in
PYPI.md
README.md
pyproject.toml
requirements-build.txt
requirements.txt
setup.py
ollex/VERSION
ollex/__init__.py
ollex/exceptions.py
ollex/version.py
ollex.egg-info/PKG-INFO
ollex.egg-info/SOURCES.txt
ollex.egg-info/dependency_links.txt
ollex.egg-info/entry_points.txt
ollex.egg-info/requires.txt
ollex.egg-info/top_level.txt
ollex/cli/__init__.py
ollex/cli/olx.py
ollex/commands/__common__.py
ollex/commands/__init__.py
ollex/commands/db.py
ollex/commands/query.py
ollex/lib/__init__.py
ollex/lib/argparse.py
ollex/lib/file.py
ollex/lib/misc.py
ollex/lib/model.py
ollex/repl/__common__.py
ollex/repl/__init__.py
ollex/repl/collection.py
ollex/repl/help.py
ollex/repl/history.py
ollex/repl/llm.py
ollex/repl/prompt.py
ollex/repl/quit.py
ollex/repl/search_results.py
ollex/repl/set.py
ollex/repl/unset.py
ollex/resources/banners.txt
ollex/resources/prompts.yaml