Metadata-Version: 2.4
Name: ollex
Version: 2.0.1
Summary: Open LLM Experimental Workbench
Home-page: https://github.com/jin-gizmo/ollex
Author: Murray Andrews
License: 3-Clause BSD License
Platform: macOS
Platform: Linux
Classifier: Development Status :: 4 - Beta
Classifier: Environment :: Console
Classifier: Intended Audience :: Developers
Classifier: Intended Audience :: Information Technology
Classifier: License :: OSI Approved :: BSD License
Classifier: Natural Language :: English
Classifier: Operating System :: MacOS
Classifier: Operating System :: POSIX :: Linux
Classifier: Programming Language :: Python :: 3 :: Only
Classifier: Topic :: Scientific/Engineering :: Artificial Intelligence
Requires-Python: >=3.11.0
License-File: LICENCE.txt
Requires-Dist: chromadb
Requires-Dist: langchain
Requires-Dist: langchain-chroma
Requires-Dist: langchain-ollama
Requires-Dist: rich
Requires-Dist: pyyaml
Requires-Dist: langchain-text-splitters
Requires-Dist: ollama
Dynamic: author
Dynamic: classifier
Dynamic: description
Dynamic: description-content-type
Dynamic: home-page
Dynamic: license
Dynamic: license-file
Dynamic: platform
Dynamic: requires-dist
Dynamic: requires-python
Dynamic: summary
